build
etc
examples
ops
pki
unimatrix
